CHANGES.txt
LICENSE.txt
MANIFEST.in
README.md
setup.py
hapiclient/__init__.py
hapiclient/hapi.py
hapiclient/hapitime.py
hapiclient/util.py
hapiclient.egg-info/PKG-INFO
hapiclient.egg-info/SOURCES.txt
hapiclient.egg-info/dependency_links.txt
hapiclient.egg-info/requires.txt
hapiclient.egg-info/top_level.txt
hapiclient/test/__init__.py
hapiclient/test/compare.py
hapiclient/test/test_chunking.py
hapiclient/test/test_datetime2hapitime.py
hapiclient/test/test_hapi.py
hapiclient/test/test_hapitime2datetime.py
hapiclient/test/test_hapitime_reformat.py