Metadata-Version: 2.1
Name: hapiclient
Version: 0.2.6
Summary: Interface to Heliophysics data server API
Home-page: http://pypi.python.org/pypi/hapiclient/
Author: Bob Weigel
Author-email: rweigel@gmu.edu
License: LICENSE.txt
License-File: LICENSE.txt
